tsfracdiff/__init__.py
tsfracdiff/tsfracdiff.py
tsfracdiff/unit_root_tests.py
tsfracdiff-1.0.4.dist-info/LICENSE
tsfracdiff-1.0.4.dist-info/METADATA
tsfracdiff-1.0.4.dist-info/WHEEL
tsfracdiff-1.0.4.dist-info/top_level.txt
tsfracdiff-1.0.4.dist-info/RECORD
