Metadata-Version: 2.1
Name: tsfracdiff
Version: 1.0.4
Summary: Efficient and easy to use fractional differentiation transformations for stationarizing time series data.
Home-page: https://github.com/adamvvu/tsfracdiff
Author: Adam Wu
Author-email: adamwu1@outlook.com
License: MIT License
Project-URL: homepage, https://github.com/adamvvu/tsfracdiff
Project-URL: documentation, https://github.com/adamvvu/tsfracdiff
Project-URL: repository, https://github.com/adamvvu/tsfracdiff
Classifier: Intended Audience :: Science/Research
Classifier: Topic :: Scientific/Engineering :: Information Analysis
Classifier: Programming Language :: Python :: 3 
Classifier: Operating System :: OS Independent
Classifier: License :: OSI Approved :: MIT License
Requires-Python: >=3.7
License-File: LICENSE
Requires-Dist: numpy
Requires-Dist: pandas
Requires-Dist: arch
Requires-Dist: joblib
